base_common_voc/__init__.py
base_common_voc/apps.py
base_common_voc/skosmos_client.py
base_common_voc/migrations/__init__.py
base_common_voc-0.2.dist-info/licenses/LICENSE
base_common_voc-0.2.dist-info/licenses/NOTICE
base_common_voc-0.2.dist-info/METADATA
base_common_voc-0.2.dist-info/WHEEL
base_common_voc-0.2.dist-info/top_level.txt
base_common_voc-0.2.dist-info/RECORD
