Metadata-Version: 2.4
Name: base-common-voc
Version: 0.2
Summary: Django app with common implementations for base Angewandte projects using the voc.uni-ak.ac.at vocabulary
License: Apache License, Version 2.0
Classifier: Intended Audience :: Developers
Classifier: Programming Language :: Python :: 3
Requires-Python: >=3.9
License-File: LICENSE
License-File: NOTICE
Requires-Dist: django>=4.2
Requires-Dist: rdflib>=7.1.4
Requires-Dist: requests>=2.32.3
Dynamic: license-file
